captivate/__init__.py
captivate-0.0.0.dist-info/LICENSE
captivate-0.0.0.dist-info/WHEEL
captivate-0.0.0.dist-info/METADATA
captivate-0.0.0.dist-info/RECORD
